lab3ajff/__init__.py
lab3ajff/common.py
lab3ajff/lab3ajff.py
lab3ajff-0.2.0.dist-info/licenses/LICENSE
lab3ajff-0.2.0.dist-info/METADATA
lab3ajff-0.2.0.dist-info/WHEEL
lab3ajff-0.2.0.dist-info/entry_points.txt
lab3ajff-0.2.0.dist-info/top_level.txt
lab3ajff-0.2.0.dist-info/RECORD
